affo_sms_service/__init__.py
affo_sms_service/application.py
affo_sms_service/cli.py
affo_sms_service/extensions.py
affo_sms_service/settings.py
affo_sms_service/wsgi.py
affo_sms_service/api/__init__.py
affo_sms_service/api/exception.py
affo_sms_service/api/sms.py
affo_sms_service/migrations/README
affo_sms_service/migrations/alembic.ini
affo_sms_service/migrations/env.py
affo_sms_service/migrations/script.py.mako
affo_sms_service/migrations/versions/c3642830841f_.py
affo_sms_service/models/__init__.py
affo_sms_service/models/sms_message.py
affo_sms_service/sms/__init__.py
affo_sms_service/sms/exception.py
affo_sms_service/sms/sms_factory.py
affo_sms_service/sms/utils.py
affo_sms_service/sms/gateways/__init__.py
affo_sms_service/sms/gateways/base.py
affo_sms_service/sms/gateways/clickatell.py
affo_sms_service/sms/gateways/twilio.py
affo_sms_service/spec/openapi.yaml
affo_sms_service-1.0.5.dist-info/LICENSE
affo_sms_service-1.0.5.dist-info/METADATA
affo_sms_service-1.0.5.dist-info/WHEEL
affo_sms_service-1.0.5.dist-info/entry_points.txt
affo_sms_service-1.0.5.dist-info/top_level.txt
affo_sms_service-1.0.5.dist-info/RECORD
