Metadata-Version: 2.1
Name: affo-sms-service
Version: 1.0.5
Summary: UNKNOWN
Home-page: https://github.com/affoio/affo-sms-service
Author: Aleksey Dalekin
Author-email: ald@affo.io
License: BSD
Keywords: sms service
Platform: any
Classifier: Development Status :: 3 - Alpha
Classifier: License :: OSI Approved :: BSD License
Classifier: Topic :: System :: Distributed Computing
Classifier: Intended Audience :: Developers
Classifier: Programming Language :: Python
Classifier: Programming Language :: Python :: 3.5
Classifier: Programming Language :: Python :: 3.6
Classifier: Programming Language :: Python :: 3.7
Classifier: Programming Language :: Python :: Implementation :: CPython
Classifier: Operating System :: OS Independent
Requires-Dist: Flask-Migrate (>=2.4.0)
Requires-Dist: Flask-SQLAlchemy (>=2.4.0)
Requires-Dist: Flask-Script (>=2.0.6)
Requires-Dist: connexion (>=2.2.0)
Requires-Dist: connexion-buzz (>=0.2.1)
Requires-Dist: dynaconf (>=2.0.3)
Requires-Dist: mysqlclient (>=1.3.13)
Requires-Dist: sentry-sdk[flask] (>=0.7.10)
Requires-Dist: twilio (>=6.12.0)
Requires-Dist: uWSGI (>=2.0.18)
